chariot_transforms/__init__.py
chariot_transforms/base.py
chariot_transforms/bbox_ops.py
chariot_transforms/augmentations/__init__.py
chariot_transforms/augmentations/transforms.py
chariot_transforms/preprocessing/__init__.py
chariot_transforms/preprocessing/clahe.py
chariot_transforms/preprocessing/transforms.py
chariot_transforms-0.2.0.dist-info/METADATA
chariot_transforms-0.2.0.dist-info/WHEEL
chariot_transforms-0.2.0.dist-info/top_level.txt
chariot_transforms-0.2.0.dist-info/RECORD
